moduleconf/__init__.py
moduleconf/config_manager.py
moduleconf/generate.py
moduleconf/testConfig.py
moduleconf-0.1.4.dist-info/LICENSE
moduleconf-0.1.4.dist-info/METADATA
moduleconf-0.1.4.dist-info/WHEEL
moduleconf-0.1.4.dist-info/top_level.txt
moduleconf-0.1.4.dist-info/RECORD
